mysql_mcp_server_ddz/__init__.py
mysql_mcp_server_ddz/server.py
mysql_mcp_server_ddz-0.2.6.dist-info/METADATA
mysql_mcp_server_ddz-0.2.6.dist-info/WHEEL
mysql_mcp_server_ddz-0.2.6.dist-info/entry_points.txt
mysql_mcp_server_ddz-0.2.6.dist-info/licenses/LICENSE
mysql_mcp_server_ddz-0.2.6.dist-info/RECORD
