Metadata-Version: 2.4
Name: mysql_mcp_server_ddz
Version: 0.2.6
Summary: A Model Context Protocol (MCP) server that enables secure interaction with MySQL databases. This server allows AI assistants to list tables, read data, and execute SQL queries through a controlled interface, making database exploration and analysis safer and more structured.
Author-email: "Dana K. Williams" <dana_w@designcomputer.com>
License-File: LICENSE
Requires-Python: >=3.11
Requires-Dist: fastmcp
Requires-Dist: mysql-connector-python>=9.1.0
